FEDI/__init__.py
FEDI/HAITCH/dMRI_HAITCH_browser.sh
FEDI/models/__init__.py
FEDI/models/common/__init__.py
FEDI/models/common/loss_functions.py
FEDI/models/pytorch/__init__.py
FEDI/models/pytorch/layers.py
FEDI/models/pytorch/models.py
FEDI/models/pytorch/sh.py
FEDI/models/tensorflow/__init__.py
FEDI/pipelines/__init__.py
FEDI/pipelines/HAITCH/dMRI_HAITCH.sh
FEDI/pipelines/HAITCH/dMRI_HAITCH_browser.sh
FEDI/pipelines/HAITCH/dMRI_HAITCH_local-config.sh
FEDI/pipelines/HAITCH/refs/acq_parameters_dMRI_scan.txt
FEDI/pipelines/HAITCH/src/Rotate_bvecs_flirt_mat.sh
FEDI/pipelines/HAITCH/src/applytransform
FEDI/pipelines/HAITCH/src/create_grad5cls_index.py
FEDI/pipelines/HAITCH/src/dicom_conversion.py
FEDI/pipelines/HAITCH/src/display_name.sh
FEDI/pipelines/HAITCH/src/dwiregistration
FEDI/pipelines/HAITCH/src/outlierdetection.py
FEDI/pipelines/HAITCH/src/rotate_bvecs_ants.py
FEDI/pipelines/HAITCH/src/segm_outliers.py
FEDI/pipelines/HAITCH/src/segment_fetalbrain.sh
FEDI/pipelines/HAITCH/src/shorerecon.py
FEDI/pipelines/HAITCH/src/update_bvecs_bvals.py
FEDI/pipelines/HAITCH/src/weights2figure.py
FEDI/sampling_scheme/HAITCH_scheme_dual_echo_sequence.dvs
FEDI/sampling_scheme/HAITCH_scheme_siemens_product_sequence.dvs
FEDI/scripts/__init__.py
FEDI/scripts/fedi_apply_transform.py
FEDI/scripts/fedi_dmri_fod.py
FEDI/scripts/fedi_dmri_moco.py
FEDI/scripts/fedi_dmri_outliers.py
FEDI/scripts/fedi_dmri_qweights.py
FEDI/scripts/fedi_dmri_recon.py
FEDI/scripts/fedi_dmri_reg.py
FEDI/scripts/fedi_dmri_rotate_bvecs.py
FEDI/scripts/fedi_dmri_snr.py
FEDI/scripts/fedi_testing_commands.py
FEDI/utils/FEDI_multi_voxel.py
FEDI/utils/FEDI_shm.py
FEDI/utils/FEDI_shore.py
FEDI/utils/__init__.py
FEDI/utils/common.py
fedi-0.2.0.dist-info/licenses/LICENSE
fedi-0.2.0.dist-info/METADATA
fedi-0.2.0.dist-info/WHEEL
fedi-0.2.0.dist-info/entry_points.txt
fedi-0.2.0.dist-info/top_level.txt
fedi-0.2.0.dist-info/RECORD
